yiku/PATH.py
yiku/__init__.py
yiku/export.py
yiku/model_warp.py
yiku/predict.py
yiku/train.py
yiku/assets/amp-test.jpg
yiku/assets/checksum.json
yiku/assets/mobilenet_v3_small.pth
yiku/assets/exec/AUTHORS
yiku/assets/exec/COPYING
yiku/assets/exec/ChangeLog
yiku/assets/exec/LICENSE.OpenSSL
yiku/assets/exec/NEWS
yiku/assets/exec/README.html
yiku/assets/exec/README.mingw
yiku/assets/exec/aria2c.exe
yiku/config/__init__.py
yiku/data/AutoLoaderSelector.py
yiku/data/SimpleDataloader.py
yiku/data/VOCdataloader.py
yiku/data/__init__.py
yiku/data/process.py
yiku/nets/__init__.py
yiku/nets/training_utils.py
yiku/nets/weights_loader.py
yiku/nets/BackBone/HGNetv2.py
yiku/nets/BackBone/MobileNetv2.py
yiku/nets/BackBone/MobileNetv3.py
yiku/nets/BackBone/STDCNet.py
yiku/nets/BackBone/Xception.py
yiku/nets/BackBone/YOLOv8.py
yiku/nets/BackBone/__init__.py
yiku/nets/Head/BaseLab.py
yiku/nets/Head/DeepLabv3plusHeader.py
yiku/nets/Head/LabHeader.py
yiku/nets/Head/__init__.py
yiku/nets/loss/Bootstrapped_CELoss.py
yiku/nets/loss/CELoss.py
yiku/nets/loss/DiceLoss.py
yiku/nets/loss/FocalLoss.py
yiku/nets/loss/__init__.py
yiku/nets/model/__init__.py
yiku/nets/model/EfficientFormerSegv2/__init__.py
yiku/nets/model/EfficientFormerSegv2/backbone.py
yiku/nets/model/EfficientFormerSegv2/model.py
yiku/nets/model/Labs/__init__.py
yiku/nets/model/Labs/labs.py
yiku/nets/model/PPLiteSeg/PPliteSeg.py
yiku/nets/model/PPLiteSeg/__init__.py
yiku/nets/model/PSPNet/__init__.py
yiku/nets/model/PSPNet/bubbliiiing_backbone.py
yiku/nets/model/PSPNet/bubbliiiing_pspnet.py
yiku/nets/model/PSPNet/yiku_pspnet.py
yiku/nets/model/SegFormer/__init__.py
yiku/nets/model/SegFormer/bubbliiiing_backbone.py
yiku/nets/model/SegFormer/bubbliiiing_segformer.py
yiku/nets/model/UNet/__init__.py
yiku/nets/model/UNet/bubbliiiing_unet.py
yiku/nets/model/UNet/hgnetv2_unet.py
yiku/nets/model/UNetplusplus/UnetPP.py
yiku/nets/model/UNetplusplus/__init__.py
yiku/nets/model/hardnet/HarDN.py
yiku/nets/model/hardnet/__init__.py
yiku_seg-0.1.5a4.dist-info/LICENSE
yiku_seg-0.1.5a4.dist-info/METADATA
yiku_seg-0.1.5a4.dist-info/WHEEL
yiku_seg-0.1.5a4.dist-info/entry_points.txt
yiku_seg-0.1.5a4.dist-info/top_level.txt
yiku_seg-0.1.5a4.dist-info/RECORD
