Metadata-Version: 2.1
Name: yiku_seg
Version: 0.1.5a4
Summary: A Segment toolkit 
Author: DrEgg
Maintainer: DrEgg
License: MIT
Keywords: machine-learning,deep-learning,vision,ML,DL,AI,ImageSegment,DeepLab,Transformer
Classifier: Programming Language :: Python :: 3
Classifier: Programming Language :: Python :: 3.8
Classifier: Programming Language :: Python :: 3.9
Classifier: Programming Language :: Python :: 3.10
Classifier: Programming Language :: Python :: 3.11
Classifier: Topic :: Software Development
Classifier: Topic :: Scientific/Engineering
Classifier: Topic :: Scientific/Engineering :: Artificial Intelligence
Classifier: Environment :: GPU :: NVIDIA CUDA
Classifier: Operating System :: POSIX :: Linux
Classifier: License :: OSI Approved :: MIT License
Classifier: Operating System :: Microsoft :: Windows
Requires-Python: >=3.8
License-File: LICENSE
Requires-Dist: matplotlib >=3.7.0
Requires-Dist: numpy >=1.24.0
Requires-Dist: onnx >=1.14.0
Requires-Dist: opencv-python >=4.4.0.0
Requires-Dist: Pillow >=9.5.0
Requires-Dist: scipy
Requires-Dist: torch
Requires-Dist: torchvision
Requires-Dist: rich
